{
  "main": {
    "title": "حلقة الإتقان - المستوى الثالث",
    "status": "جارية الآن",
    "desc": "مراجعة سورة البقرة والتركيز على أحكام النون الساكنة",
    "students": 12
  },
  "stats": {
    "active": 3,
    "students": 42,
    "growth": 12
  },
  "sessions": [
    {
      "id": 1,
      "title": "حلقة حفظ الصغار(أ)",
      "students": 12,
      "time": "04:00 - 05:30",
      "status": "active"
    },
    {
      "id": 2,
      "title": "حلقة التجويد العملي",
      "students": 8,
      "time": "06:00 - 07:30",
      "status": "list"
    },
    {
      "id": 3,
      "title": "حلقة المتون العلمية",
      "students": 15,
      "time": "08:30 - 10:00",
      "status": "list"
    }
  ],
  "weekly": [1, 0.3, 1, 0.2, 1, 0.4, 1]
}